Lab1-Counter-master/Lab1-Counter-master/task1/counter.sv
module counter #(
    parameter width = 8
)(
    input  logic clk,
    input  logic rst,
    input  logic en,
    output logic [width-1:0] count
);

always_ff @(posedge clk) begin
    if (rst) begin
        count <= {width{1'b0}};
    end else if (en) begin
        count <= count + 1'b1;
    end
end

endmodule

Lab1-Counter-master/Lab1-Counter-master/task1/counter.vcd
$version Generated by VerilatedVcd $end
$date Thu Oct 16 11:56:36 2025 $end
$timescale 1ps $end

 $scope module TOP $end
  $var wire  1 # clk $end
  $var wire  8 & count [7:0] $end
  $var wire  1 % en $end
  $var wire  1 $ rst $end
  $scope module counter $end
   $var wire  1 # clk $end
   $var wire  8 & count [7:0] $end
   $var wire  1 % en $end
   $var wire  1 $ rst $end
   $var wire 32 ' width [31:0] $end
  $upscope $end
 $upscope $end
$enddefinitions $end


#0
1#
1$
0%
b00000000 &
b00000000000000000000000000001000 '
#5
0#
#10
1#
#15
0#
#20
1#
#25
0#
#30
1#
0$
#35
0#
#40
1#
#45
0#
#50
1#
#55
0#
#60
1#
1%
#65
0#
#70
1#
b00000001 &
#75
0#
#80
1#
b00000010 &
#85
0#
#90
1#
b00000011 &
#95
0#
#100
1#
b00000100 &
#105
0#
#110
1#
b00000101 &
#115
0#
#120
1#
b00000110 &
#125
0#
#130
1#
b00000111 &
#135
0#
#140
1#
b00001000 &
#145
0#
#150
1#
b00001001 &
#155
0#
#160
1#
1$
0%
b00001010 &
#165
0#
#170
1#
0$
b00000000 &
